LICENSE
MANIFEST.in
README.rst
setup.py
mele/__init__.py
mele/beat.py
melebeats.egg-info/PKG-INFO
melebeats.egg-info/SOURCES.txt
melebeats.egg-info/dependency_links.txt
melebeats.egg-info/entry_points.txt
melebeats.egg-info/not-zip-safe
melebeats.egg-info/requires.txt
melebeats.egg-info/top_level.txt