Metadata-Version: 1.0
Name: melebeats
Version: 0.3
Summary: for the lolz
Home-page: https://github.com/Chive/melebeats
Author: Kim Thoenen
Author-email: kim@smuzey.ch
License: MIT
Platform: OS Independent
